Metadata-Version: 2.1
Name: django-fernet-fields2
Version: 0.6
Summary: Fernet-encrypted model fields for Django
Home-page: https://github.com/eba-alemayehu/django-fernet-fields/
Author: ORCAS, Inc
Author-email: orcastech@orcasinc.com
Classifier: Environment :: Web Environment
Classifier: Intended Audience :: Developers
Classifier: License :: OSI Approved :: BSD License
Classifier: Operating System :: OS Independent
Classifier: Programming Language :: Python
Classifier: Programming Language :: Python :: 2
Classifier: Programming Language :: Python :: 2.7
Classifier: Programming Language :: Python :: 3
Classifier: Programming Language :: Python :: 3.5
Classifier: Programming Language :: Python :: 3.6
Classifier: Programming Language :: Python :: 3.7
Classifier: Programming Language :: Python :: Implementation :: CPython
Classifier: Programming Language :: Python :: Implementation :: PyPy
Classifier: Framework :: Django
License-File: LICENSE.txt
License-File: AUTHORS.rst
Requires-Dist: Django>=1.11
Requires-Dist: cryptography>=0.9
